MANIFEST.in
README.rst
html_linter.py
setup.cfg
setup.py
html_linter.egg-info/PKG-INFO
html_linter.egg-info/SOURCES.txt
html_linter.egg-info/dependency_links.txt
html_linter.egg-info/requires.txt
html_linter.egg-info/top_level.txt
scripts/html_lint.py
test/test_html_linter.py